slutil/__init__.py
slutil/adapters/abstract_repository.py
slutil/adapters/abstract_slurm_service.py
slutil/adapters/abstract_vcs.py
slutil/adapters/csv_repository.py
slutil/adapters/git.py
slutil/adapters/slurm.py
slutil/cli/cmd_delete.py
slutil/cli/cmd_edit.py
slutil/cli/cmd_filter.py
slutil/cli/cmd_report.py
slutil/cli/cmd_status.py
slutil/cli/cmd_submit.py
slutil/cli/cmd_undelete.py
slutil/cli/command_factory.py
slutil/cli/formatter.py
slutil/main.py
slutil/model/Record.py
slutil/services/abstract_uow.py
slutil/services/csv_uow.py
slutil/services/services.py
slutil-0.10.3.dist-info/LICENSE.md
slutil-0.10.3.dist-info/WHEEL
slutil-0.10.3.dist-info/METADATA
slutil-0.10.3.dist-info/entry_points.txt
slutil-0.10.3.dist-info/RECORD
