Metadata-Version: 2.1
Name: slutil
Version: 0.10.3
Summary: Command-line utility to view slurm jobs
Author: Eugene Prout
Author-email: eugene.prout1@gmail.com
Requires-Python: >=3.7,<4.0
Classifier: Programming Language :: Python :: 3
Classifier: Programming Language :: Python :: 3.7
Classifier: Programming Language :: Python :: 3.8
Classifier: Programming Language :: Python :: 3.9
Classifier: Programming Language :: Python :: 3.10
Classifier: Programming Language :: Python :: 3.11
Requires-Dist: click (>=8.1.3,<9.0.0)
Requires-Dist: rich (>=13.3.1,<14.0.0)
